{"entities":{"636 Copy Room":{"seat":"f6s001","x":"50%","y":"37%"},"705 Xerox Color":{"seat":"f7s001","x":"99%","y":"43%"},"727 Canon Black+White":{"seat":"f7s002","x":"17%","y":"67%"},"812 Canon Black+White":{"seat":"f8s001","x":"4%","y":"55%"},"819 Xerox Color":{"seat":"f8s002","x":"96%","y":"41%"},"Cecelia Staub":{"seat":"f7s003","x":"49%","y":"15%"},"Aaron Bouvier":{"seat":"f8s003","x":"60%","y":"2%"},"Agustina CLEANER":{"seat":"f7s004","x":"24%","y":"62%"},"Al Merry/194":{"seat":"f7s005","x":"99%","y":"52%"},"Alex Maiorov/148":{"seat":"f7s006","x":"7%","y":"43%"},"Alex Scaros/8":{"seat":"f6s002","x":"44%","y":"80%"},"Alex Ledford/152":{"seat":"f7s007","x":"80%","y":"72%"},"Alex Doomany/220":{"seat":"f8s004","x":"99%","y":"36%"},"Alexey Novikov/201":{"seat":"f7s008","x":"17%","y":"53%"},"Alexis Bynum/230":{"seat":"f8s005","x":"49%","y":"78%"},"Ali Berk/229":{"seat":"f8s006","x":"37%","y":"0%"},"Alison Joseph/271":{"seat":"f6s003","x":"56%","y":"75%"},"Alison Hill/183":{"seat":"f7s009","x":"48%","y":"57%"},"Allison Kim/117":{"seat":"f6s004","x":"93%","y":"20%"},"Amanda Tellier/95":{"seat":"f6s005","x":"49%","y":"54%"},"Amy Dold/98":{"seat":"f6s006","x":"52%","y":"46%"},"Amy Abrahams/119":{"seat":"f6s007","x":"99%","y":"42%"},"Andre Poli/176":{"seat":"f7s010","x":"51%","y":"23%"},"Andrew Jasperson/158":{"seat":"f7s011","x":"97%","y":"15%"},"Andrew Coppola/244":{"seat":"f8s007","x":"16%","y":"75%"},"Anjali Patel/82":{"seat":"f6s008","x":"54%","y":"17%"},"Anthony Moschini/196":{"seat":"f7s012","x":"61%","y":"42%"},"Ava Rant/213":{"seat":"f8s008","x":"48%","y":"70%"},"Bambi Scott":{"seat":"f6s009","x":"90%","y":"88%"},"Bat Cave .":{"seat":null,"x":"","y":""},"Blair Warren/168":{"seat":"f7s013","x":"18%","y":"77%"},"Branden Bouvia/53":{"seat":"f6s010","x":"94%","y":"87%"},"Brandon Pracht/32":{"seat":"f6s011","x":"70%","y":"25%"},"Brandon Henderson/126":{"seat":"f7s014","x":"55%","y":"76%"},"Breck Henson/210":{"seat":"f8s009","x":"63%","y":"99%"},"Brian Schimpf/160":{"seat":"f7s015","x":"92%","y":"7%"},"Brian Metcalf/260":{"seat":"f8s010","x":"93%","y":"49%"},"Brit Fryer/45":{"seat":"f6s012","x":"11%","y":"67%"},"Bryce Schroer-Shepord/100":{"seat":"f6s013","x":"27%","y":"92%"},"Cait Collette/14":{"seat":"f6s014","x":"41%","y":"76%"},"Caleb Jensen/125":{"seat":"f7s016","x":"56%","y":"57%"},"Carie Susee/251":{"seat":"f8s011","x":"80%","y":"17%"},"Carl Jannerfeldt/172":{"seat":"f7s017","x":"90%","y":"65%"},"Carolina (Caro) Hernandez/224":{"seat":"f8s012","x":"35%","y":"99%"},"Casey Jennings/28":{"seat":"f6s015","x":"89%","y":"3%"},"Catherine O'Neill/105":{"seat":"f6s016","x":"37%","y":"96%"},"Cayleigh Griffin/198":{"seat":"f7s018","x":"17%","y":"62%"},"Charles Duncan/143":{"seat":"f7s019","x":"49%","y":"78%"},"Chass Reyes/236":{"seat":"f8s013","x":"25%","y":"85%"},"Cheryl Warbrook/187":{"seat":"f7s020","x":"19%","y":"15%"},"Chris Whalley/255":{"seat":"f8s014","x":"22%","y":"87%"},"Chris McClelland/275":{"seat":"f8s015","x":"74%","y":"40%"},"Chris Kelsch/271":{"seat":"f8s016","x":"82%","y":"38%"},"Chris Mills":{"seat":"f8s017","x":"46%","y":"79%"},"Christina Smith/115":{"seat":"f6s017","x":"25%","y":"31%"},"Christine Mason/122":{"seat":"f6s018","x":"84%","y":"20%"},"Christine Young/200":{"seat":"f7s021","x":"25%","y":"37%"},"Christopher Momenee/48":{"seat":"f8s018","x":"31%","y":"20%"},"Colleen Decourcy":{"seat":"f8s019","x":"73%","y":"85%"},"Conor Dooley/SL6":{"seat":"f7s022","x":"90%","y":"19%"},"Coral Gables Springs .":{"seat":"f6s019","x":"62%","y":"20%"},"Cory Chonko/219":{"seat":"f8s020","x":"98%","y":"36%"},"Cory\n Everett/150":{"seat":"f7s023","x":"78%","y":"54%"},"Courtney Bernstein/22":{"seat":"f6s020","x":"56%","y":"60%"},"Craig Blagg/133":{"seat":"f7s024","x":"69%","y":"70%"},"Crystal Moore/113":{"seat":"f6s021","x":"57%","y":"8%"},"Crystal Winstead/68":{"seat":"f6s022","x":"57%","y":"64%"},"Danielle Rounds/104":{"seat":"f8s021","x":"4%","y":"66%"},"Danielle Mentes/84":{"seat":"f6s023","x":"44%","y":"31%"},"David Kolbusz/2":{"seat":"f6s024","x":"17%","y":"90%"},"David Spradlin/SL1":{"seat":"f7s025","x":"99%","y":"48%"},"David Niblick":{"seat":"f8s022","x":"13%","y":"52%"},"David Stopforth/61":{"seat":"f6s025","x":"26%","y":"16%"},"Deb Rosen/135":{"seat":"f7s026","x":"42%","y":"25%"},"Deborah Graham/243":{"seat":"f8s023","x":"93%","y":"69%"},"Den .":{"seat":"f8s024","x":"23%","y":"8%"},"Desiree White/235":{"seat":"f8s025","x":"93%","y":"7%"},"Diego de Moya CLEANER":{"seat":"f7s027","x":"8%","y":"53%"},"Dom Tunon/182":{"seat":"f7s028","x":"92%","y":"10%"},"Dominique Brown/57":{"seat":"f6s026","x":"61%","y":"3%"},"Eden Weingart/262":{"seat":"f8s026","x":"39%","y":"67%"},"Elfranko Wessels":{"seat":"f8s027","x":"72%","y":"12%"},"Elizabeth Sova/88":{"seat":"f6s027","x":"16%","y":"55%"},"Emily Longfield/197":{"seat":"f7s029","x":"76%","y":"17%"},"Emily Dods/90":{"seat":"f6s028","x":"51%","y":"57%"},"Eric Johnson/SL2":{"seat":"f7s030","x":"3%","y":"86%"},"Eric\n Helin/137":{"seat":"f7s031","x":"68%","y":"10%"},"Eric Dennis":{"seat":"f7s032","x":"26%","y":"3%"},"Erica Bartuccelli":{"seat":"f7s033","x":"36%","y":"8%"},"Erik Norin/128":{"seat":"f7s034","x":"15%","y":"38%"},"Erwin Federizo/138":{"seat":"f7s035","x":"70%","y":"49%"},"Esai Ramirez/SL5":{"seat":"f7s036","x":"60%","y":"83%"},"Evan Elberson/SL4":{"seat":"f7s037","x":"39%","y":"28%"},"Frank Suarez/237":{"seat":"f8s028","x":"88%","y":"95%"},"Frank Gregory":{"seat":"f6s029","x":"54%","y":"24%"},"Fred Lee":{"seat":"f6s030","x":"97%","y":"19%"},"Garrett Hoy/87":{"seat":"f6s031","x":"36%","y":"74%"},"Garrick Sheldon/174":{"seat":"f7s038","x":"68%","y":"61%"},"Gary Van Dzura/123":{"seat":"f7s039","x":"27%","y":"52%"},"Gina Chang/89":{"seat":"f6s032","x":"15%","y":"64%"},"Helen Park/166":{"seat":"f7s040","x":"5%","y":"45%"},"Hosanna Marshal/191":{"seat":"f8s029","x":"86%","y":"9%"},"Howard Finkelstein/14":{"seat":"f7s041","x":"87%","y":"18%"},"Hunter Fine/132":{"seat":"f7s042","x":"87%","y":"34%"},"Ian Hart/155":{"seat":"f7s043","x":"28%","y":"14%"},"Ian Young/108":{"seat":"f6s033","x":"95%","y":"8%"},"Ina Choi/77":{"seat":"f6s034","x":"92%","y":"74%"},"Jaclyn Crowley/190":{"seat":"f7s044","x":"23%","y":"38%"},"Jacque Sloan/56":{"seat":"f6s035","x":"9%","y":"83%"},"Jacqueline Ventura/65":{"seat":"f6s036","x":"82%","y":"60%"},"Jacqueline Tierney/112":{"seat":"f6s037","x":"71%","y":"58%"},"Jacquelyn Williams/114":{"seat":"f6s038","x":"26%","y":"61%"},"Jaime Robinson/3":{"seat":"f6s039","x":"9%","y":"6%"},"James Williams":{"seat":"f6s040","x":"72%","y":"88%"},"James Hughes/259":{"seat":"f8s030","x":"47%","y":"5%"},"James Koutsouvanos/118":{"seat":"f6s041","x":"80%","y":"49%"},"James Mohan/239A":{"seat":"f8s031","x":"61%","y":"67%"},"Jasmina Almeda/18":{"seat":"f6s042","x":"39%","y":"79%"},"Jasmine Cogdell/21":{"seat":"f6s043","x":"33%","y":"78%"},"Jason Pelton/221":{"seat":"f8s032","x":"21%","y":"10%"},"Jeane Wong-Marotta/102":{"seat":"f6s044","x":"57%","y":"62%"},"Jed Heuer/154":{"seat":"f7s045","x":"98%","y":"67%"},"Jeff Cha/67":{"seat":"f6s045","x":"57%","y":"89%"},"Jeff Goldstone/48":{"seat":"f8s033","x":"6%","y":"35%"},"Jen Vladimirsky/202":{"seat":"f7s046","x":"8%","y":"68%"},"Jeremy Hogan/253":{"seat":"f8s034","x":"32%","y":"71%"},"Jerico Cabaysa/37":{"seat":"f6s046","x":"9%","y":"85%"},"Jesse Corinella/276":{"seat":"f8s035","x":"22%","y":"78%"},"Jesse Derosa/73":{"seat":"f6s047","x":"85%","y":"21%"},"Jessi Ortolano/70":{"seat":"f6s048","x":"37%","y":"52%"},"Jessica Martinaitis/58":{"seat":"f6s049","x":"4%","y":"35%"},"Jessica Shriftman/167":{"seat":"f7s047","x":"2%","y":"94%"},"Jessica Abercrombie/23":{"seat":"f6s050","x":"99%","y":"4%"},"Jill Kearton/254":{"seat":"f8s036","x":"55%","y":"80%"},"Jimm Lasser/124":{"seat":"f7s048","x":"92%","y":"17%"},"Jimmy Kan/206":{"seat":"f7s049","x":"29%","y":"59%"},"Joe Morelli/9":{"seat":"f6s051","x":"40%","y":"62%"},"Joe Zhou/147":{"seat":"f7s050","x":"13%","y":"71%"},"John Parker/129":{"seat":"f7s051","x":"85%","y":"49%"},"Jolande Van Helbergen/HR Office":{"seat":"f8s037","x":"58%","y":"89%"},"Jonathan Chu/38":{"seat":"f6s052","x":"22%","y":"100%"},"Jonathan Percy/186":{"seat":"f7s052","x":"70%","y":"63%"},"Joseph Zisa/111":{"seat":"f6s053","x":"73%","y":"49%"},"Justin Lam/55":{"seat":"f6s054","x":"24%","y":"85%"},"Justin Dean/91":{"seat":"f6s055","x":"61%","y":"21%"},"Justine Lowe/209":{"seat":"f8s038","x":"33%","y":"94%"},"Karlo Cordova/54":{"seat":"f6s056","x":"41%","y":"59%"},"Karri Jinkins":{"seat":"f7s053","x":"5%","y":"73%"},"Kasey Donnelly/106":{"seat":"f6s057","x":"44%","y":"37%"},"Kate Smith/250":{"seat":"f8s039","x":"71%","y":"52%"},"Kate Bauer/134":{"seat":"f7s054","x":"33%","y":"73%"},"Katie Hoak/4":{"seat":"f6s058","x":"71%","y":"60%"},"Kellie Pederson/165":{"seat":"f7s055","x":"28%","y":"73%"},"Kelly Parrotto/163":{"seat":"f7s056","x":"65%","y":"73%"},"Keri Rommel/211":{"seat":"f8s040","x":"73%","y":"65%"},"Kerry O'Connell/10":{"seat":"f6s059","x":"36%","y":"34%"},"Kevin Walker":{"seat":"f8s041","x":"86%","y":"19%"},"Kevin Wilkerson/50":{"seat":"f6s060","x":"26%","y":"3%"},"Kiara Hidalgo/240":{"seat":"f8s042","x":"74%","y":"34%"},"Kim Haxton/131":{"seat":"f7s057","x":"14%","y":"83%"},"Knuckles .":{"seat":"f6s061","x":"87%","y":"89%"},"Kristen Herrington/20":{"seat":"f6s062","x":"15%","y":"86%"},"Kristen Althoff/252":{"seat":"f8s043","x":"48%","y":"9%"},"Kristen McNamee/109":{"seat":"f6s063","x":"76%","y":"51%"},"Kristen Johnson/184":{"seat":"f7s058","x":"66%","y":"93%"},"Kristen Wright/62":{"seat":"f6s064","x":"37%","y":"99%"},"Kristin Daly/216":{"seat":"f8s044","x":"64%","y":"87%"},"Kristin Gladney":{"seat":"f8s045","x":"91%","y":"91%"},"Kyle Glackin/30":{"seat":"f6s065","x":"8%","y":"29%"},"Laddie Peterson/192":{"seat":"f7s059","x":"79%","y":"48%"},"Laura Mechling/273":{"seat":"f8s046","x":"32%","y":"50%"},"Laura Prior/107":{"seat":"f6s066","x":"99%","y":"25%"},"Lauren Amato/212":{"seat":"f8s047","x":"13%","y":"33%"},"Lauren Smith/13":{"seat":"f6s067","x":"3%","y":"45%"},"Lindsey Timko/227":{"seat":"f8s048","x":"24%","y":"16%"},"Lisa Deloney/195":{"seat":"f7s060","x":"39%","y":"77%"},"Liz Lindberg/11":{"seat":"f6s068","x":"33%","y":"91%"},"Liz Taylor/16":{"seat":"f6s069","x":"92%","y":"5%"},"Lori Vanore/204":{"seat":"f7s061","x":"45%","y":"14%"},"Lorin Brown/266":{"seat":"f8s049","x":"50%","y":"95%"},"Lovedeep Singh/245":{"seat":"f8s050","x":"22%","y":"7%"},"Luiza Naritomi/180":{"seat":"f7s062","x":"96%","y":"60%"},"Luke Sacherman/157":{"seat":"f7s063","x":"14%","y":"6%"},"Luke Reyes-Guerra-Dunn/99":{"seat":"f6s070","x":"84%","y":"46%"},"Maja Cule/258":{"seat":"f8s051","x":"13%","y":"38%"},"Man vs. Meat .":{"seat":"f7s064","x":"61%","y":"16%"},"Marcelino CLEANER":{"seat":"f7s065","x":"74%","y":"43%"},"Marcelle Forsyth/51":{"seat":"f6s071","x":"93%","y":"68%"},"Marissa Moody/42":{"seat":"f6s072","x":"27%","y":"12%"},"Mark Malloy/92":{"seat":"f6s073","x":"86%","y":"79%"},"Martine McCarthy":{"seat":"f6s074","x":"81%","y":"9%"},"Mathieu Zarbatany/166":{"seat":"f7s066","x":"47%","y":"1%"},"Matt Simpson/44":{"seat":"f6s075","x":"95%","y":"98%"},"Mauricio Ruiz/177":{"seat":"f7s067","x":"92%","y":"45%"},"Meghan Mullen/17":{"seat":"f6s076","x":"89%","y":"96%"},"Michael Vitiello/151":{"seat":"f7s068","x":"35%","y":"80%"},"Michelle Carman/161":{"seat":"f7s069","x":"90%","y":"32%"},"Michelle Mandell/49":{"seat":"f6s077","x":"37%","y":"26%"},"Michelle Lasso/41":{"seat":"f6s078","x":"63%","y":"23%"},"Mike Welch/34":{"seat":"f6s079","x":"57%","y":"70%"},"Mike Giepert/62":{"seat":"f7s070","x":"60%","y":"62%"},"Mike Nesi/269":{"seat":"f8s052","x":"54%","y":"25%"},"Mindy Haake/59":{"seat":"f6s080","x":"49%","y":"35%"},"Molly Friedman/5":{"seat":"f6s081","x":"92%","y":"3%"},"Molly Jamison":{"seat":"f7s071","x":"71%","y":"99%"},"Munk's Lunch .":{"seat":null,"x":"","y":""},"Mutaurwa Mapondera/203":{"seat":"f7s072","x":"12%","y":"55%"},"Nathan Dalessandro/274":{"seat":"f8s053","x":"93%","y":"76%"},"Neal Arthur/1":{"seat":"f6s082","x":"15%","y":"14%"},"Neil Sawhney/75":{"seat":"f6s083","x":"74%","y":"73%"},"Nelson .":{"seat":"f7s073","x":"11%","y":"49%"},"Nick Setounski/189":{"seat":"f7s074","x":"33%","y":"51%"},"NJ Placentra/153":{"seat":"f7s075","x":"71%","y":"96%"},"Nursing Room":{"seat":"f6s084","x":"99%","y":"33%"},"Orlee Tatarka/185":{"seat":"f7s076","x":"76%","y":"15%"},"Patrick Cahill/25":{"seat":"f6s085","x":"52%","y":"98%"},"Patrick Mauro/72":{"seat":"f6s086","x":"79%","y":"9%"},"Patrick O'Donohuge/228":{"seat":"f8s054","x":"26%","y":"21%"},"Patty Ehinger/6":{"seat":"f6s087","x":"64%","y":"78%"},"Paul Phillips":{"seat":"f7s077","x":"73%","y":"95%"},"Peggy Richardson/241":{"seat":"f8s055","x":"87%","y":"52%"},"Pepe (Jose') Hernandez/169":{"seat":"f7s078","x":"2%","y":"2%"},"Phone Booth 6":{"seat":"f6s088","x":"10%","y":"16%"},"Phone Booth 7 A":{"seat":"f7s079","x":"13%","y":"62%"},"Phone Booth 7 B":{"seat":"f7s080","x":"35%","y":"3%"},"Pietro Clemente/198":{"seat":"f8s056","x":"57%","y":"52%"},"Price Manford/27":{"seat":"f6s089","x":"8%","y":"10%"},"Priscilla Gomez/179":{"seat":"f7s081","x":"21%","y":"93%"},"Rajeev Basu/171":{"seat":"f7s082","x":"45%","y":"31%"},"Ricardo Robinson/272":{"seat":"f8s057","x":"72%","y":"13%"},"Rick Jacques/156":{"seat":"f7s083","x":"35%","y":"13%"},"Robert Perksy/101":{"seat":"f6s090","x":"13%","y":"0%"},"Rose Sacktor/159":{"seat":"f7s084","x":"29%","y":"0%"},"Roshen Carman/139":{"seat":"f7s085","x":"37%","y":"12%"},"Rosie Geozalian/SL3":{"seat":"f7s086","x":"59%","y":"63%"},"Ryan Haskins/47":{"seat":"f6s091","x":"30%","y":"29%"},"Rylee Millerd/226":{"seat":"f8s058","x":"56%","y":"50%"},"Sam Matthews/12":{"seat":"f6s092","x":"64%","y":"73%"},"Samantha Wagner/19":{"seat":"f6s093","x":"31%","y":"46%"},"Samantha Renison/103":{"seat":"f6s094","x":"72%","y":"5%"},"Sara Jagielski/208":{"seat":"f8s059","x":"19%","y":"44%"},"Sasithon Pooviriyakal":{"seat":"f8s060","x":"7%","y":"90%"},"Sean McLaughlin/130":{"seat":"f7s087","x":"76%","y":"47%"},"Sean Jones/145":{"seat":"f7s088","x":"12%","y":"84%"},"Serifcan Ozcan/136":{"seat":"f7s089","x":"46%","y":"77%"},"Seth Zarkin/120":{"seat":"f6s095","x":"15%","y":"40%"},"Shane Thompson/245":{"seat":"f8s061","x":"15%","y":"60%"},"Sonia Bisono/225":{"seat":"f8s062","x":"31%","y":"47%"},"Squirrel's Hatch .":{"seat":"f8s063","x":"54%","y":"1%"},"Stefanie Sorge/104":{"seat":"f6s096","x":"38%","y":"30%"},"Stephen Nelson/161B":{"seat":"f7s090","x":"98%","y":"89%"},"Stuart Jennings/127":{"seat":"f7s091","x":"47%","y":"87%"},"Sunjoo Ryou/101":{"seat":"f8s064","x":"52%","y":"5%"},"Tara Kaimal/76":{"seat":"f6s097","x":"6%","y":"11%"},"Tara Kennedy/52":{"seat":"f6s098","x":"98%","y":"11%"},"Tara Fray":{"seat":"f6s099","x":"70%","y":"4%"},"Temma Shoaf/181":{"seat":"f7s092","x":"87%","y":"5%"},"Terrell Stanback":{"seat":"f7s093","x":"30%","y":"21%"},"test test":{"seat":null,"x":"","y":""},"Toby Hussey/31":{"seat":"f6s100","x":"83%","y":"75%"},"Todd Epstein/69":{"seat":"f6s101","x":"70%","y":"37%"},"Toliver Roebuck/175":{"seat":"f7s094","x":"6%","y":"21%"},"Tom Gibby/26":{"seat":"f6s102","x":"93%","y":"47%"},"Tory Nettleton/140":{"seat":"f7s095","x":"44%","y":"27%"},"Trevor Gilley/170":{"seat":"f7s096","x":"58%","y":"47%"},"Turkey Tuesday .":{"seat":"f6s103","x":"10%","y":"62%"},"Veal Chop .":{"seat":"f6s104","x":"23%","y":"68%"},"Vinnie Gareffa/207":{"seat":"f7s097","x":"25%","y":"50%"},"Vlad Behar":{"seat":"f6s105","x":"81%","y":"74%"},"War Room .":{"seat":"f6s106","x":"92%","y":"10%"},"Wes Young/48":{"seat":"f6s107","x":"77%","y":"13%"},"Will Binder/173":{"seat":"f7s098","x":"38%","y":"50%"},"Winner's Circle .":{"seat":"f7s099","x":"71%","y":"61%"},"Yann Samuels/64":{"seat":"f6s108","x":"89%","y":"36%"},"Yisette CLEANER":{"seat":"f7s100","x":"76%","y":"22%"},"Yoni Freedman/78":{"seat":"f6s109","x":"54%","y":"84%"},"Yui Uchida/161A":{"seat":"f7s101","x":"37%","y":"3%"}},"seats":{"f6s001":{"x":"50%","y":"37%"},"f6s002":{"x":"44%","y":"80%"},"f6s003":{"x":"56%","y":"75%"},"f6s004":{"x":"93%","y":"20%"},"f6s005":{"x":"49%","y":"54%"},"f6s006":{"x":"52%","y":"46%"},"f6s007":{"x":"99%","y":"42%"},"f6s008":{"x":"54%","y":"17%"},"f6s009":{"x":"90%","y":"88%"},"f6s010":{"x":"94%","y":"87%"},"f6s011":{"x":"70%","y":"25%"},"f6s012":{"x":"11%","y":"67%"},"f6s013":{"x":"27%","y":"92%"},"f6s014":{"x":"41%","y":"76%"},"f6s015":{"x":"89%","y":"3%"},"f6s016":{"x":"37%","y":"96%"},"f6s017":{"x":"25%","y":"31%"},"f6s018":{"x":"84%","y":"20%"},"f6s019":{"x":"62%","y":"20%"},"f6s020":{"x":"56%","y":"60%"},"f6s021":{"x":"57%","y":"8%"},"f6s022":{"x":"57%","y":"64%"},"f6s023":{"x":"44%","y":"31%"},"f6s024":{"x":"17%","y":"90%"},"f6s025":{"x":"26%","y":"16%"},"f6s026":{"x":"61%","y":"3%"},"f6s027":{"x":"16%","y":"55%"},"f6s028":{"x":"51%","y":"57%"},"f6s029":{"x":"54%","y":"24%"},"f6s030":{"x":"97%","y":"19%"},"f6s031":{"x":"36%","y":"74%"},"f6s032":{"x":"15%","y":"64%"},"f6s033":{"x":"95%","y":"8%"},"f6s034":{"x":"92%","y":"74%"},"f6s035":{"x":"9%","y":"83%"},"f6s036":{"x":"82%","y":"60%"},"f6s037":{"x":"71%","y":"58%"},"f6s038":{"x":"26%","y":"61%"},"f6s039":{"x":"9%","y":"6%"},"f6s040":{"x":"72%","y":"88%"},"f6s041":{"x":"80%","y":"49%"},"f6s042":{"x":"39%","y":"79%"},"f6s043":{"x":"33%","y":"78%"},"f6s044":{"x":"57%","y":"62%"},"f6s045":{"x":"57%","y":"89%"},"f6s046":{"x":"9%","y":"85%"},"f6s047":{"x":"85%","y":"21%"},"f6s048":{"x":"37%","y":"52%"},"f6s049":{"x":"4%","y":"35%"},"f6s050":{"x":"99%","y":"4%"},"f6s051":{"x":"40%","y":"62%"},"f6s052":{"x":"22%","y":"100%"},"f6s053":{"x":"73%","y":"49%"},"f6s054":{"x":"24%","y":"85%"},"f6s055":{"x":"61%","y":"21%"},"f6s056":{"x":"41%","y":"59%"},"f6s057":{"x":"44%","y":"37%"},"f6s058":{"x":"71%","y":"60%"},"f6s059":{"x":"36%","y":"34%"},"f6s060":{"x":"26%","y":"3%"},"f6s061":{"x":"87%","y":"89%"},"f6s062":{"x":"15%","y":"86%"},"f6s063":{"x":"76%","y":"51%"},"f6s064":{"x":"37%","y":"99%"},"f6s065":{"x":"8%","y":"29%"},"f6s066":{"x":"99%","y":"25%"},"f6s067":{"x":"3%","y":"45%"},"f6s068":{"x":"33%","y":"91%"},"f6s069":{"x":"92%","y":"5%"},"f6s070":{"x":"84%","y":"46%"},"f6s071":{"x":"93%","y":"68%"},"f6s072":{"x":"27%","y":"12%"},"f6s073":{"x":"86%","y":"79%"},"f6s074":{"x":"81%","y":"9%"},"f6s075":{"x":"95%","y":"98%"},"f6s076":{"x":"89%","y":"96%"},"f6s077":{"x":"37%","y":"26%"},"f6s078":{"x":"63%","y":"23%"},"f6s079":{"x":"57%","y":"70%"},"f6s080":{"x":"49%","y":"35%"},"f6s081":{"x":"92%","y":"3%"},"f6s082":{"x":"15%","y":"14%"},"f6s083":{"x":"74%","y":"73%"},"f6s084":{"x":"99%","y":"33%"},"f6s085":{"x":"52%","y":"98%"},"f6s086":{"x":"79%","y":"9%"},"f6s087":{"x":"64%","y":"78%"},"f6s088":{"x":"10%","y":"16%"},"f6s089":{"x":"8%","y":"10%"},"f6s090":{"x":"13%","y":"0%"},"f6s091":{"x":"30%","y":"29%"},"f6s092":{"x":"64%","y":"73%"},"f6s093":{"x":"31%","y":"46%"},"f6s094":{"x":"72%","y":"5%"},"f6s095":{"x":"15%","y":"40%"},"f6s096":{"x":"38%","y":"30%"},"f6s097":{"x":"6%","y":"11%"},"f6s098":{"x":"98%","y":"11%"},"f6s099":{"x":"70%","y":"4%"},"f6s100":{"x":"83%","y":"75%"},"f6s101":{"x":"70%","y":"37%"},"f6s102":{"x":"93%","y":"47%"},"f6s103":{"x":"10%","y":"62%"},"f6s104":{"x":"23%","y":"68%"},"f6s105":{"x":"81%","y":"74%"},"f6s106":{"x":"92%","y":"10%"},"f6s107":{"x":"77%","y":"13%"},"f6s108":{"x":"89%","y":"36%"},"f6s109":{"x":"54%","y":"84%"},"f6s110":{"x":"21%","y":"60%"},"f6s111":{"x":"89%","y":"14%"},"f6s112":{"x":"13%","y":"7%"},"f6s113":{"x":"11%","y":"59%"},"f6s114":{"x":"64%","y":"5%"},"f6s115":{"x":"62%","y":"10%"},"f6s116":{"x":"88%","y":"97%"},"f6s117":{"x":"77%","y":"53%"},"f6s118":{"x":"86%","y":"47%"},"f6s119":{"x":"73%","y":"49%"},"f6s120":{"x":"6%","y":"32%"},"f6s121":{"x":"47%","y":"80%"},"f6s122":{"x":"59%","y":"52%"},"f6s123":{"x":"36%","y":"46%"},"f6s124":{"x":"93%","y":"40%"},"f6s125":{"x":"51%","y":"26%"},"f6s126":{"x":"34%","y":"90%"},"f6s127":{"x":"61%","y":"47%"},"f6s128":{"x":"3%","y":"84%"},"f6s129":{"x":"25%","y":"64%"},"f6s130":{"x":"85%","y":"43%"},"f6s131":{"x":"85%","y":"27%"},"f6s132":{"x":"64%","y":"79%"},"f6s133":{"x":"42%","y":"26%"},"f6s134":{"x":"81%","y":"84%"},"f6s135":{"x":"89%","y":"54%"},"f6s136":{"x":"71%","y":"90%"},"f6s137":{"x":"53%","y":"99%"},"f6s138":{"x":"25%","y":"67%"},"f6s139":{"x":"65%","y":"49%"},"f6s140":{"x":"44%","y":"36%"},"f6s141":{"x":"66%","y":"20%"},"f6s142":{"x":"30%","y":"82%"},"f6s143":{"x":"88%","y":"92%"},"f6s144":{"x":"63%","y":"33%"},"f6s145":{"x":"8%","y":"15%"},"f6s146":{"x":"76%","y":"63%"},"f6s147":{"x":"28%","y":"44%"},"f6s148":{"x":"83%","y":"23%"},"f6s149":{"x":"67%","y":"75%"},"f6s150":{"x":"33%","y":"20%"},"f7s001":{"x":"99%","y":"43%"},"f7s002":{"x":"17%","y":"67%"},"f7s003":{"x":"49%","y":"15%"},"f7s004":{"x":"24%","y":"62%"},"f7s005":{"x":"99%","y":"52%"},"f7s006":{"x":"7%","y":"43%"},"f7s007":{"x":"80%","y":"72%"},"f7s008":{"x":"17%","y":"53%"},"f7s009":{"x":"48%","y":"57%"},"f7s010":{"x":"51%","y":"23%"},"f7s011":{"x":"97%","y":"15%"},"f7s012":{"x":"61%","y":"42%"},"f7s013":{"x":"18%","y":"77%"},"f7s014":{"x":"55%","y":"76%"},"f7s015":{"x":"92%","y":"7%"},"f7s016":{"x":"56%","y":"57%"},"f7s017":{"x":"90%","y":"65%"},"f7s018":{"x":"17%","y":"62%"},"f7s019":{"x":"49%","y":"78%"},"f7s020":{"x":"19%","y":"15%"},"f7s021":{"x":"25%","y":"37%"},"f7s022":{"x":"90%","y":"19%"},"f7s023":{"x":"78%","y":"54%"},"f7s024":{"x":"69%","y":"70%"},"f7s025":{"x":"99%","y":"48%"},"f7s026":{"x":"42%","y":"25%"},"f7s027":{"x":"8%","y":"53%"},"f7s028":{"x":"92%","y":"10%"},"f7s029":{"x":"76%","y":"17%"},"f7s030":{"x":"3%","y":"86%"},"f7s031":{"x":"68%","y":"10%"},"f7s032":{"x":"26%","y":"3%"},"f7s033":{"x":"36%","y":"8%"},"f7s034":{"x":"15%","y":"38%"},"f7s035":{"x":"70%","y":"49%"},"f7s036":{"x":"60%","y":"83%"},"f7s037":{"x":"39%","y":"28%"},"f7s038":{"x":"68%","y":"61%"},"f7s039":{"x":"27%","y":"52%"},"f7s040":{"x":"5%","y":"45%"},"f7s041":{"x":"87%","y":"18%"},"f7s042":{"x":"87%","y":"34%"},"f7s043":{"x":"28%","y":"14%"},"f7s044":{"x":"23%","y":"38%"},"f7s045":{"x":"98%","y":"67%"},"f7s046":{"x":"8%","y":"68%"},"f7s047":{"x":"2%","y":"94%"},"f7s048":{"x":"92%","y":"17%"},"f7s049":{"x":"29%","y":"59%"},"f7s050":{"x":"13%","y":"71%"},"f7s051":{"x":"85%","y":"49%"},"f7s052":{"x":"70%","y":"63%"},"f7s053":{"x":"5%","y":"73%"},"f7s054":{"x":"33%","y":"73%"},"f7s055":{"x":"28%","y":"73%"},"f7s056":{"x":"65%","y":"73%"},"f7s057":{"x":"14%","y":"83%"},"f7s058":{"x":"66%","y":"93%"},"f7s059":{"x":"79%","y":"48%"},"f7s060":{"x":"39%","y":"77%"},"f7s061":{"x":"45%","y":"14%"},"f7s062":{"x":"96%","y":"60%"},"f7s063":{"x":"14%","y":"6%"},"f7s064":{"x":"61%","y":"16%"},"f7s065":{"x":"74%","y":"43%"},"f7s066":{"x":"47%","y":"1%"},"f7s067":{"x":"92%","y":"45%"},"f7s068":{"x":"35%","y":"80%"},"f7s069":{"x":"90%","y":"32%"},"f7s070":{"x":"60%","y":"62%"},"f7s071":{"x":"71%","y":"99%"},"f7s072":{"x":"12%","y":"55%"},"f7s073":{"x":"11%","y":"49%"},"f7s074":{"x":"33%","y":"51%"},"f7s075":{"x":"71%","y":"96%"},"f7s076":{"x":"76%","y":"15%"},"f7s077":{"x":"73%","y":"95%"},"f7s078":{"x":"2%","y":"2%"},"f7s079":{"x":"13%","y":"62%"},"f7s080":{"x":"35%","y":"3%"},"f7s081":{"x":"21%","y":"93%"},"f7s082":{"x":"45%","y":"31%"},"f7s083":{"x":"35%","y":"13%"},"f7s084":{"x":"29%","y":"0%"},"f7s085":{"x":"37%","y":"12%"},"f7s086":{"x":"59%","y":"63%"},"f7s087":{"x":"76%","y":"47%"},"f7s088":{"x":"12%","y":"84%"},"f7s089":{"x":"46%","y":"77%"},"f7s090":{"x":"98%","y":"89%"},"f7s091":{"x":"47%","y":"87%"},"f7s092":{"x":"87%","y":"5%"},"f7s093":{"x":"30%","y":"21%"},"f7s094":{"x":"6%","y":"21%"},"f7s095":{"x":"44%","y":"27%"},"f7s096":{"x":"58%","y":"47%"},"f7s097":{"x":"25%","y":"50%"},"f7s098":{"x":"38%","y":"50%"},"f7s099":{"x":"71%","y":"61%"},"f7s100":{"x":"76%","y":"22%"},"f7s101":{"x":"37%","y":"3%"},"f7s102":{"x":"81%","y":"14%"},"f7s103":{"x":"19%","y":"90%"},"f7s104":{"x":"81%","y":"60%"},"f7s105":{"x":"78%","y":"27%"},"f7s106":{"x":"64%","y":"9%"},"f7s107":{"x":"98%","y":"6%"},"f7s108":{"x":"49%","y":"35%"},"f7s109":{"x":"90%","y":"55%"},"f7s110":{"x":"67%","y":"13%"},"f7s111":{"x":"56%","y":"52%"},"f7s112":{"x":"2%","y":"52%"},"f7s113":{"x":"10%","y":"19%"},"f7s114":{"x":"18%","y":"1%"},"f7s115":{"x":"52%","y":"10%"},"f7s116":{"x":"77%","y":"27%"},"f7s117":{"x":"57%","y":"14%"},"f7s118":{"x":"22%","y":"88%"},"f7s119":{"x":"30%","y":"100%"},"f7s120":{"x":"12%","y":"93%"},"f7s121":{"x":"14%","y":"59%"},"f7s122":{"x":"39%","y":"6%"},"f7s123":{"x":"83%","y":"50%"},"f7s124":{"x":"76%","y":"78%"},"f7s125":{"x":"81%","y":"59%"},"f7s126":{"x":"48%","y":"43%"},"f7s127":{"x":"81%","y":"5%"},"f7s128":{"x":"29%","y":"67%"},"f7s129":{"x":"36%","y":"36%"},"f7s130":{"x":"40%","y":"37%"},"f7s131":{"x":"84%","y":"50%"},"f7s132":{"x":"91%","y":"39%"},"f7s133":{"x":"49%","y":"18%"},"f7s134":{"x":"81%","y":"46%"},"f7s135":{"x":"40%","y":"95%"},"f7s136":{"x":"22%","y":"73%"},"f7s137":{"x":"8%","y":"88%"},"f7s138":{"x":"54%","y":"22%"},"f7s139":{"x":"47%","y":"45%"},"f7s140":{"x":"7%","y":"76%"},"f7s141":{"x":"38%","y":"13%"},"f7s142":{"x":"86%","y":"19%"},"f7s143":{"x":"83%","y":"85%"},"f7s144":{"x":"52%","y":"82%"},"f7s145":{"x":"86%","y":"82%"},"f7s146":{"x":"44%","y":"67%"},"f7s147":{"x":"53%","y":"34%"},"f7s148":{"x":"3%","y":"72%"},"f7s149":{"x":"88%","y":"43%"},"f7s150":{"x":"2%","y":"52%"},"f8s001":{"x":"4%","y":"55%"},"f8s002":{"x":"96%","y":"41%"},"f8s003":{"x":"60%","y":"2%"},"f8s004":{"x":"99%","y":"36%"},"f8s005":{"x":"49%","y":"78%"},"f8s006":{"x":"37%","y":"0%"},"f8s007":{"x":"16%","y":"75%"},"f8s008":{"x":"48%","y":"70%"},"f8s009":{"x":"63%","y":"99%"},"f8s010":{"x":"93%","y":"49%"},"f8s011":{"x":"80%","y":"17%"},"f8s012":{"x":"35%","y":"99%"},"f8s013":{"x":"25%","y":"85%"},"f8s014":{"x":"22%","y":"87%"},"f8s015":{"x":"74%","y":"40%"},"f8s016":{"x":"82%","y":"38%"},"f8s017":{"x":"46%","y":"79%"},"f8s018":{"x":"31%","y":"20%"},"f8s019":{"x":"73%","y":"85%"},"f8s020":{"x":"98%","y":"36%"},"f8s021":{"x":"4%","y":"66%"},"f8s022":{"x":"13%","y":"52%"},"f8s023":{"x":"93%","y":"69%"},"f8s024":{"x":"23%","y":"8%"},"f8s025":{"x":"93%","y":"7%"},"f8s026":{"x":"39%","y":"67%"},"f8s027":{"x":"72%","y":"12%"},"f8s028":{"x":"88%","y":"95%"},"f8s029":{"x":"86%","y":"9%"},"f8s030":{"x":"47%","y":"5%"},"f8s031":{"x":"61%","y":"67%"},"f8s032":{"x":"21%","y":"10%"},"f8s033":{"x":"6%","y":"35%"},"f8s034":{"x":"32%","y":"71%"},"f8s035":{"x":"22%","y":"78%"},"f8s036":{"x":"55%","y":"80%"},"f8s037":{"x":"58%","y":"89%"},"f8s038":{"x":"33%","y":"94%"},"f8s039":{"x":"71%","y":"52%"},"f8s040":{"x":"73%","y":"65%"},"f8s041":{"x":"86%","y":"19%"},"f8s042":{"x":"74%","y":"34%"},"f8s043":{"x":"48%","y":"9%"},"f8s044":{"x":"64%","y":"87%"},"f8s045":{"x":"91%","y":"91%"},"f8s046":{"x":"32%","y":"50%"},"f8s047":{"x":"13%","y":"33%"},"f8s048":{"x":"24%","y":"16%"},"f8s049":{"x":"50%","y":"95%"},"f8s050":{"x":"22%","y":"7%"},"f8s051":{"x":"13%","y":"38%"},"f8s052":{"x":"54%","y":"25%"},"f8s053":{"x":"93%","y":"76%"},"f8s054":{"x":"26%","y":"21%"},"f8s055":{"x":"87%","y":"52%"},"f8s056":{"x":"57%","y":"52%"},"f8s057":{"x":"72%","y":"13%"},"f8s058":{"x":"56%","y":"50%"},"f8s059":{"x":"19%","y":"44%"},"f8s060":{"x":"7%","y":"90%"},"f8s061":{"x":"15%","y":"60%"},"f8s062":{"x":"31%","y":"47%"},"f8s063":{"x":"54%","y":"1%"},"f8s064":{"x":"52%","y":"5%"},"f8s065":{"x":"21%","y":"3%"},"f8s066":{"x":"34%","y":"97%"},"f8s067":{"x":"99%","y":"50%"},"f8s068":{"x":"2%","y":"68%"},"f8s069":{"x":"12%","y":"34%"},"f8s070":{"x":"25%","y":"95%"},"f8s071":{"x":"38%","y":"57%"},"f8s072":{"x":"20%","y":"72%"},"f8s073":{"x":"89%","y":"63%"},"f8s074":{"x":"94%","y":"73%"},"f8s075":{"x":"15%","y":"95%"},"f8s076":{"x":"87%","y":"82%"},"f8s077":{"x":"88%","y":"96%"},"f8s078":{"x":"99%","y":"94%"},"f8s079":{"x":"59%","y":"76%"},"f8s080":{"x":"72%","y":"9%"},"f8s081":{"x":"26%","y":"13%"},"f8s082":{"x":"12%","y":"11%"},"f8s083":{"x":"49%","y":"32%"},"f8s084":{"x":"41%","y":"98%"},"f8s085":{"x":"77%","y":"46%"},"f8s086":{"x":"62%","y":"29%"},"f8s087":{"x":"2%","y":"94%"},"f8s088":{"x":"94%","y":"76%"},"f8s089":{"x":"71%","y":"55%"},"f8s090":{"x":"63%","y":"57%"},"f8s091":{"x":"99%","y":"82%"},"f8s092":{"x":"28%","y":"80%"},"f8s093":{"x":"69%","y":"25%"},"f8s094":{"x":"69%","y":"8%"},"f8s095":{"x":"62%","y":"62%"},"f8s096":{"x":"65%","y":"80%"},"f8s097":{"x":"31%","y":"78%"},"f8s098":{"x":"18%","y":"46%"},"f8s099":{"x":"20%","y":"83%"},"f8s100":{"x":"64%","y":"49%"},"f8s101":{"x":"76%","y":"30%"},"f8s102":{"x":"79%","y":"80%"},"f8s103":{"x":"90%","y":"54%"},"f8s104":{"x":"70%","y":"99%"},"f8s105":{"x":"24%","y":"61%"},"f8s106":{"x":"92%","y":"38%"},"f8s107":{"x":"52%","y":"20%"},"f8s108":{"x":"32%","y":"22%"},"f8s109":{"x":"6%","y":"12%"},"f8s110":{"x":"16%","y":"57%"},"f8s111":{"x":"93%","y":"98%"},"f8s112":{"x":"85%","y":"57%"},"f8s113":{"x":"52%","y":"11%"},"f8s114":{"x":"52%","y":"52%"},"f8s115":{"x":"77%","y":"16%"},"f8s116":{"x":"75%","y":"8%"},"f8s117":{"x":"98%","y":"2%"},"f8s118":{"x":"98%","y":"23%"},"f8s119":{"x":"23%","y":"96%"},"f8s120":{"x":"93%","y":"15%"},"f8s121":{"x":"13%","y":"53%"},"f8s122":{"x":"8%","y":"49%"},"f8s123":{"x":"9%","y":"75%"},"f8s124":{"x":"69%","y":"81%"},"f8s125":{"x":"29%","y":"24%"},"f8s126":{"x":"66%","y":"78%"},"f8s127":{"x":"95%","y":"16%"},"f8s128":{"x":"68%","y":"68%"},"f8s129":{"x":"46%","y":"70%"},"f8s130":{"x":"45%","y":"91%"},"f8s131":{"x":"21%","y":"99%"},"f8s132":{"x":"10%","y":"38%"},"f8s133":{"x":"80%","y":"6%"},"f8s134":{"x":"80%","y":"75%"},"f8s135":{"x":"67%","y":"32%"},"f8s136":{"x":"97%","y":"58%"},"f8s137":{"x":"32%","y":"36%"},"f8s138":{"x":"19%","y":"58%"},"f8s139":{"x":"82%","y":"86%"},"f8s140":{"x":"46%","y":"44%"},"f8s141":{"x":"38%","y":"58%"},"f8s142":{"x":"58%","y":"96%"},"f8s143":{"x":"87%","y":"5%"},"f8s144":{"x":"80%","y":"5%"},"f8s145":{"x":"41%","y":"15%"},"f8s146":{"x":"14%","y":"30%"},"f8s147":{"x":"99%","y":"97%"},"f8s148":{"x":"98%","y":"47%"},"f8s149":{"x":"15%","y":"37%"},"f8s150":{"x":"65%","y":"2%"}}}